spanclient/__init__.py
spanclient/_client.py
spanclient/_endpoint_wrapper.py
spanclient/_handle_responses.py
spanclient/_request_obj.py
spanclient/_response_data.py
spanclient/_typing.py
spanclient/_version.py
spanclient/test_utils/__init__.py
spanclient/test_utils/_errors.py
spanclient/test_utils/_mock_response.py
spanclient/test_utils/_patch_aio.py
spanclient/test_utils/_req_validator.py
spanclient-0.2.2.dist-info/LICENSE
spanclient-0.2.2.dist-info/METADATA
spanclient-0.2.2.dist-info/WHEEL
spanclient-0.2.2.dist-info/top_level.txt
spanclient-0.2.2.dist-info/RECORD
